accolade-3.0.dist-info/METADATA
accolade-3.0.dist-info/RECORD
accolade-3.0.dist-info/WHEEL
accolade-3.0.dist-info/top_level.txt
cliparser/__init__.py
cliparser/argparser.py
cliparser/os.py
cliparser/play.py
cliparser/sa.py
parser/__init__.py
parser/argparser.py
parser/os.py
parser/play.py
parser/sa.py
