Metadata-Version: 2.1
Name: accolade
Version: 3.0
Summary: Accolade CLI
Home-page: UNKNOWN
Author: J.V.
Author-email: UNKNOWN
License: UNKNOWN
Platform: UNKNOWN
